{"timestamp":"2025-11-11T17:40:59.217804-05:00","source":{"id":"cli/database/interpret-results","name":"CodeQL CLI: database interpret-results"},"plaintextMessage":"A fatal error occurred: Could not process query metadata for C:\\Users\\Nikhil\\25-26\\759\\UntrustIDE\\databases\\git-graph\\results\\getting-started\\codeql-extra-queries-javascript\\dataflow\\vscode-getConfiguration-node.bqrs.\r\nError was: Expected result pattern(s) are not present for path-problem query: Expected at least two result patterns. These should include at least an 'edges' result set (see https://codeql.github.com/docs/writing-codeql-queries/creating-path-queries/). [INVALID_RESULT_PATTERNS]","severity":"error","visibility":{"telemetry":false},"attributes":{"exitCode":2}}
